eatcook.py
eatcook-0.1.2.1.dist-info/entry_points.txt
eatcook-0.1.2.1.dist-info/WHEEL
eatcook-0.1.2.1.dist-info/METADATA
eatcook-0.1.2.1.dist-info/RECORD
