Metadata-Version: 2.1
Name: eatcook
Version: 0.1.2.1
Summary: Mini HTTP Server.
Author: Porplax
Author-email: saynemarsh9@gmail.com
Requires-Python: >=3.6,<4.0
Classifier: Programming Language :: Python :: 3
Classifier: Programming Language :: Python :: 3.6
Classifier: Programming Language :: Python :: 3.7
Classifier: Programming Language :: Python :: 3.8
Classifier: Programming Language :: Python :: 3.9
Classifier: Programming Language :: Python :: 3.10
Requires-Dist: colorama (>=0.4.5,<0.5.0)
Requires-Dist: typer[all] (>=0.1.0,<0.2.0)
